conffey/Console.py
conffey/Document.py
conffey/Picture.py
conffey/__init__.py
conffey-5.0.0.dist-info/LICENSE
conffey-5.0.0.dist-info/METADATA
conffey-5.0.0.dist-info/WHEEL
conffey-5.0.0.dist-info/top_level.txt
conffey-5.0.0.dist-info/RECORD
