Metadata-Version: 2.1
Name: conffey
Version: 5.0.0
Summary: A library that encapsulates various functions of Python.
Home-page: https://github.com/super-took/conffey
Author: C.Z.F.
Author-email: 3023639843@qq.com
Maintainer: C.Z.F.
Maintainer-email: 3023639843@qq.com
License: BSD License
Platform: all
Classifier: Development Status :: 4 - Beta
Classifier: Operating System :: OS Independent
Classifier: Intended Audience :: Developers
Classifier: License :: OSI Approved :: BSD License
Classifier: Programming Language :: Python
Classifier: Programming Language :: Python :: Implementation :: CPython
Classifier: Programming Language :: Python :: 3
Classifier: Programming Language :: Python :: 3.6
Classifier: Programming Language :: Python :: 3.7
Classifier: Programming Language :: Python :: 3.8
Classifier: Topic :: Software Development :: Libraries
Requires-Python: >=3.6.0
Requires-Dist: xpinyin (>=0.5.6)
Requires-Dist: Pillow (>=7.0.0)
Requires-Dist: PyPDF2 (>=1.26.0)
Requires-Dist: opencv-python (>=4.2.0.32)
Requires-Dist: MyQR (>=2.3.1)
Requires-Dist: pyzbar (>=0.1.8)
Requires-Dist: pydub (>=0.24.1)
